<?xml version = '1.0' encoding = 'UTF-8'?>
<Diagram class="oracle.dbtools.crest.swingui.relational.DPVRelational" name="Relational_1" id="6C2062B2-0030-F0AC-7AA1-C7341C623C84">
<createdBy>GGG</createdBy>
<modifiedBy>GGG</modifiedBy>
<createdTime>2024-02-22 08:07:00 UTC</createdTime>
<autoRoute>false</autoRoute>
<boxInbox>true</boxInbox>
<showLegend>false</showLegend>
<showLabels>false</showLabels>
<showRelAttributes>false</showRelAttributes>
<gridEnabled>false</gridEnabled>
<showGrid>false</showGrid>
<diagramColor>-1</diagramColor>
<display>false</display>
<notation>1</notation>
<objectViews>
<OView class="oracle.dbtools.crest.swingui.relational.TVTable" oid="DD61AE77-A693-863A-0F80-8A061E71285B" otype="Table" vid="5CBEB53F-548F-0F48-7334-FF9C9C4D5ABD">
<hideElementsInCurrentOnly>false</hideElementsInCurrentOnly>
<bounds x="20" y="20" width="221" height="204"/>
</OView>
</objectViews>
</Diagram>